backlib/__init__.py
backlib/saves/settings.bin
backlib/saves/settings.log
backlib/saves/settings_backup.bin
backlib/saves/maps/EXTRA new pvp for players.msav
backlib/saves/maps/[red]carboned extraordinallity.msav
backlib/saves/maps/destiny of PASTA.msav
backlib/saves/maps/new pvp for players.msav
backlib/saves/mod_tools/keycode.bak
backlib/saves/mod_tools/keycode.json
backlib/saves/mod_tools/mod-tools-config.bak
backlib/saves/mod_tools/mod-tools-config.hjson
backlib/saves/mod_tools/fonts/README.txt
backlib/saves/mod_tools/startup/README.txt
backlib/saves/mod_tools/ui/colors.json
backlib/saves/mod_tools/ui/styles.json
backlib/saves/mods/3snake3sapphirium.zip
backlib/saves/mods/apszoldatmindustrymappingutilities.zip
backlib/saves/mods/aureusstratusexogenesis.zip
backlib/saves/mods/catana791fading-revelations.zip
backlib/saves/mods/mark4d4esoteric.zip
backlib/saves/mods/sova444-compressing-mod-030e97d1.zip
backlib/saves/mods/sova444-supreme-compressing-mod.zip
backlib/saves/mods/vvseangtvvproject-restoration.zip
backlib/saves/mods/yuria-shikibenewhorizonmod.zip
backlib/saves/previews/1-cache_v2.dat
backlib/saves/previews/10-cache_v2.dat
backlib/saves/previews/10_v2.png
backlib/saves/previews/1_v2.png
backlib/saves/previews/1xcroptiumx-cache_v2.dat
backlib/saves/previews/1xcroptiumx_v2.png
backlib/saves/previews/2-cache_v2.dat
backlib/saves/previews/2_v2.png
backlib/saves/previews/2truxtion-cache_v2.dat
backlib/saves/previews/2truxtion_v2.png
backlib/saves/previews/3-cache_v2.dat
backlib/saves/previews/3_v2.png
backlib/saves/previews/3lightium-cache_v2.dat
backlib/saves/previews/3lightium_v2.png
backlib/saves/previews/4-cache_v2.dat
backlib/saves/previews/4_v2.png
backlib/saves/previews/5-cache_v2.dat
backlib/saves/previews/5_v2.png
backlib/saves/previews/6-cache_v2.dat
backlib/saves/previews/6_v2.png
backlib/saves/previews/AtlasCitadel-cache_v2.dat
backlib/saves/previews/AtlasCitadel_v2.png
backlib/saves/previews/Beastcav-cache_v2.dat
hyperpool8-0.0.0.1.dist-info/METADATA
hyperpool8-0.0.0.1.dist-info/WHEEL
hyperpool8-0.0.0.1.dist-info/licenses/LICENSE
hyperpool8-0.0.0.1.dist-info/RECORD
